{"stats":{"minecraft:used":{"minecraft:painting":1,"minecraft:villager_spawn_egg":1,"minecraft:jukebox":1},"minecraft:custom":{"minecraft:talked_to_villager":4,"minecraft:time_since_rest":5224,"minecraft:walk_one_cm":11242,"minecraft:leave_game":1,"minecraft:walk_under_water_one_cm":644,"minecraft:damage_taken":160,"minecraft:play_time":5393,"minecraft:jump":60,"minecraft:time_since_death":5192,"minecraft:sprint_one_cm":9961,"minecraft:total_world_time":5445,"minecraft:fly_one_cm":5768,"minecraft:deaths":1}},"DataVersion":4440}