{"stats":{"minecraft:used":{"minecraft:crafting_table":1,"minecraft:piglin_spawn_egg":2},"minecraft:dropped":{"gzlf:jbyarmor_helmet":2,"gzlf:musicdiscjby":129},"minecraft:crafted":{"gzlf:jbyblock":9,"minecraft:gold_nugget":9,"gzlf:silvernugget":9,"gzlf:silveringot":1,"gzlf:musicdiscjby":81},"minecraft:custom":{"minecraft:interact_with_crafting_table":5,"minecraft:time_since_rest":4598,"minecraft:walk_one_cm":114,"minecraft:total_world_time":4641,"minecraft:leave_game":1,"minecraft:fly_one_cm":3959,"minecraft:sneak_time":37,"minecraft:play_time":4598,"minecraft:jump":1,"minecraft:time_since_death":4598,"minecraft:drop":131},"minecraft:picked_up":{"gzlf:musicdiscjby":96,"gzlf:jbyarmor_helmet":1}},"DataVersion":4440}